tpcti/__init__.py
tpcti/_client.py
tpcti/_util.py
tpcti-0.0.2.dist-info/METADATA
tpcti-0.0.2.dist-info/WHEEL
tpcti-0.0.2.dist-info/top_level.txt
tpcti-0.0.2.dist-info/RECORD
