Metadata-Version: 2.4
Name: tpcti
Version: 0.0.2
Summary: package
Author-email: khah <trchikhanhfrv@gmail.com>
License: MIT
Requires-Python: >=3.8
